aiogram_navigation/filters/__init__.py
aiogram_navigation/filters/statedata.py
aiogram_navigation/middleware/__init__.py
aiogram_navigation/middleware/navigator.py
aiogram_navigation/reply/__init__.py
aiogram_navigation/reply/navigation.py
aiogram_navigation/reply/replymenu.py
aiogram_navigation/utils/__init__.py
aiogram_navigation/utils/handlerwrapper.py
aiogram_navigation-0.0.4.dist-info/licenses/LICENSE
aiogram_navigation-0.0.4.dist-info/METADATA
aiogram_navigation-0.0.4.dist-info/WHEEL
aiogram_navigation-0.0.4.dist-info/top_level.txt
aiogram_navigation-0.0.4.dist-info/RECORD
