Metadata-Version: 2.4
Name: aiogram-navigation
Version: 0.0.4
Summary: Navigation system for aiogram
Author-email: Vladimir Batsura <batsura.vs@gmail.com>
License-Expression: MIT
Project-URL: Homepage, https://github.com/batsura-vs/aiogram-navigation
Project-URL: Issues, https://github.com/batsura-vs/aiogram-navigation/issues
Classifier: Programming Language :: Python :: 3
Classifier: Operating System :: OS Independent
Requires-Python: >=3.10
License-File: LICENSE
Dynamic: license-file
